onnx4acumos/__init__.py
onnx4acumos/_version.py
onnx4acumos/acumos_onnx_onboarding.py
onnx4acumos/Templates/onnxClientTemplate.py
onnx4acumos/Templates/onnxModelOnBoardingTemplate.py
onnx4acumos-1.0.5.dist-info/METADATA
onnx4acumos-1.0.5.dist-info/WHEEL
onnx4acumos-1.0.5.dist-info/entry_points.txt
onnx4acumos-1.0.5.dist-info/top_level.txt
onnx4acumos-1.0.5.dist-info/RECORD
