Metadata-Version: 2.1
Name: onnx4acumos
Version: 1.0.5
Summary: Acumos ONNX client library for pushing Onnx models in Acumos
Home-page: https://gerrit.acumos.org/r/gitweb?p=acumos-onnx-client.git
Author: Bruno Lozach
Author-email: bruno.lozach@orange.com
License: Apache License 2.0
Keywords: acumos machine learning model modeling artificial intelligence ml ai onnx
Platform: UNKNOWN
Classifier: Development Status :: 4 - Beta
Classifier: Intended Audience :: Developers
Classifier: Intended Audience :: Science/Research
Classifier: Programming Language :: Python :: 3
Classifier: Programming Language :: Python :: 3.6
Classifier: Programming Language :: Python :: 3.7
Classifier: Programming Language :: Python :: 3.8
Classifier: License :: OSI Approved :: Apache Software License
Requires-Python: >=3.6, <3.9
Requires-Dist: protobuf
Requires-Dist: requests
Requires-Dist: numpy
Requires-Dist: configparser
Requires-Dist: dill
Requires-Dist: appdirs
Requires-Dist: filelock
Requires-Dist: grpcio
Requires-Dist: zipp
Requires-Dist: acumos
Requires-Dist: acumos-model-runner
Requires-Dist: onnx
Requires-Dist: onnxruntime
Requires-Dist: typing-inspect
